securesystemslib/__init__.py
securesystemslib/dsse.py
securesystemslib/exceptions.py
securesystemslib/formats.py
securesystemslib/hash.py
securesystemslib/py.typed
securesystemslib/storage.py
securesystemslib/_gpg/__init__.py
securesystemslib/_gpg/common.py
securesystemslib/_gpg/constants.py
securesystemslib/_gpg/dsa.py
securesystemslib/_gpg/eddsa.py
securesystemslib/_gpg/exceptions.py
securesystemslib/_gpg/functions.py
securesystemslib/_gpg/handlers.py
securesystemslib/_gpg/rsa.py
securesystemslib/_gpg/util.py
securesystemslib/_internal/utils.py
securesystemslib/_vendor/README.md
securesystemslib/_vendor/__init__.py
securesystemslib/_vendor/test-ed25519-upstream.sh
securesystemslib/_vendor/ed25519/.gitignore
securesystemslib/_vendor/ed25519/LICENSE
securesystemslib/_vendor/ed25519/README.rst
securesystemslib/_vendor/ed25519/__init__.py
securesystemslib/_vendor/ed25519/ed25519.py
securesystemslib/_vendor/ed25519/science.py
securesystemslib/_vendor/ed25519/test_ed25519.py
securesystemslib/_vendor/ed25519/test_data/ed25519
securesystemslib/signer/__init__.py
securesystemslib/signer/_aws_signer.py
securesystemslib/signer/_azure_signer.py
securesystemslib/signer/_crypto_signer.py
securesystemslib/signer/_crypto_utils.py
securesystemslib/signer/_gcp_signer.py
securesystemslib/signer/_gpg_signer.py
securesystemslib/signer/_hsm_signer.py
securesystemslib/signer/_key.py
securesystemslib/signer/_signature.py
securesystemslib/signer/_signer.py
securesystemslib/signer/_sigstore_signer.py
securesystemslib/signer/_spx_signer.py
securesystemslib/signer/_utils.py
securesystemslib/signer/_vault_signer.py
securesystemslib-1.3.0.dist-info/METADATA
securesystemslib-1.3.0.dist-info/WHEEL
securesystemslib-1.3.0.dist-info/licenses/LICENSE
securesystemslib-1.3.0.dist-info/RECORD
