Metadata-Version: 2.4
Name: securesystemslib
Version: 1.3.0
Summary: A library that provides cryptographic and general-purpose routines for Secure Systems Lab projects at NYU
Project-URL: Homepage, https://github.com/secure-systems-lab/securesystemslib
Project-URL: Source, https://github.com/secure-systems-lab/securesystemslib
Project-URL: Issues, https://github.com/secure-systems-lab/securesystemslib/issues
Author-email: "https://www.updateframework.com" <theupdateframework@googlegroups.com>
License-Expression: MIT
License-File: LICENSE
Keywords: cryptography,ecdsa,ed25519,keys,rsa,signatures
Classifier: Development Status :: 4 - Beta
Classifier: Intended Audience :: Developers
Classifier: Natural Language :: English
Classifier: Operating System :: MacOS :: MacOS X
Classifier: Operating System :: Microsoft :: Windows
Classifier: Operating System :: POSIX
Classifier: Operating System :: POSIX :: Linux
Classifier: Programming Language :: Python :: 3
Classifier: Programming Language :: Python :: 3.9
Classifier: Programming Language :: Python :: 3.10
Classifier: Programming Language :: Python :: 3.11
Classifier: Programming Language :: Python :: 3.12
Classifier: Programming Language :: Python :: 3.13
Classifier: Programming Language :: Python :: Implementation :: CPython
Classifier: Topic :: Security
Classifier: Topic :: Software Development
Requires-Python: ~=3.8
Provides-Extra: awskms
Requires-Dist: boto3; extra == 'awskms'
Requires-Dist: botocore; extra == 'awskms'
Requires-Dist: cryptography>=40.0.0; extra == 'awskms'
Provides-Extra: azurekms
Requires-Dist: azure-identity; extra == 'azurekms'
Requires-Dist: azure-keyvault-keys; extra == 'azurekms'
Requires-Dist: cryptography>=40.0.0; extra == 'azurekms'
Provides-Extra: crypto
Requires-Dist: cryptography>=40.0.0; extra == 'crypto'
Provides-Extra: gcpkms
Requires-Dist: cryptography>=40.0.0; extra == 'gcpkms'
Requires-Dist: google-cloud-kms; extra == 'gcpkms'
Provides-Extra: hsm
Requires-Dist: asn1crypto; extra == 'hsm'
Requires-Dist: cryptography>=40.0.0; extra == 'hsm'
Requires-Dist: pykcs11; extra == 'hsm'
Provides-Extra: pyspx
Requires-Dist: pyspx>=0.5.0; extra == 'pyspx'
Provides-Extra: sigstore
Requires-Dist: sigstore~=3.0; extra == 'sigstore'
Provides-Extra: vault
Requires-Dist: cryptography>=40.0.0; extra == 'vault'
Requires-Dist: hvac; extra == 'vault'
